[
	{
		"english": "drink",
		"batak": "minum"
	},
	{
		"english": "fragrant",
		"batak": "angur"
	},
	{
		"english": "shortly",
		"batak": "satokkin"
	},
	{
		"english": "age",
		"batak": "umur"
	},
	{
		"english": "all",
		"batak": "sude"
	},
	{
		"english": "almost",
		"batak": "laho"
	},
	{
		"english": "also",
		"batak": "muse, pe"
	},
	{
		"english": "always",
		"batak": "torus"
	},
	{
		"english": "amazing",
		"batak": "ulihian"
	},
	{
		"english": "and",
		"batak": "dohot"
	},
	{
		"english": "at",
		"batak": "di"
	},
	{
		"english": "awful",
		"batak": "hassitan, ngerihian"
	},
	{
		"english": "baby",
		"batak": "posoposo, pesepese"
	},
	{
		"english": "kid",
		"batak": "dakdanak"
	},
	{
		"english": "child",
		"batak": "geleng"
	},
	{
		"english": "ugly",
		"batak": "roa"
	},
	{
		"english": "bad",
		"batak": "jahat, buruk"
	},
	{
		"english": "bag",
		"batak": "tas, hajut"
	},
	{
		"english": "great",
		"batak": "bongak"
	},
	{
		"english": "beautiful",
		"batak": "bagak"
	},
	{
		"english": "because",
		"batak": "alani"
	},
	{
		"english": "near",
		"batak": "jonok"
	},
	{
		"english": "beside",
		"batak": "jenek"
	},
	{
		"english": "good",
		"batak": "denggan"
	},
	{
		"english": "between",
		"batak": "golakni"
	},
	{
		"english": "bicycle",
		"batak": "lereng"
	},
	{
		"english": "bill",
		"batak": "bon"
	},
	{
		"english": "bird",
		"batak": "andukur"
	},
	{
		"english": "bitter",
		"batak": "migar"
	},
	{
		"english": "blood",
		"batak": "mudar"
	},
	{
		"english": "book",
		"batak": "sijahaon"
	},
	{
		"english": "boss",
		"batak": "tokke"
	},
	{
		"english": "boy",
		"batak": "baowa"
	},
	{
		"english": "brave",
		"batak": "barani"
	},
	{
		"english": "bread",
		"batak": "kue"
	},
	{
		"english": "broken",
		"batak": "sega, malengleng"
	},
	{
		"english": "busy",
		"batak": "repot"
	},
	{
		"english": "camera",
		"batak": "tustel"
	},
	{
		"english": "can",
		"batak": "boi"
	},
	{
		"english": "canoe",
		"batak": "solu"
	},
	{
		"english": "careful",
		"batak": "nanget-nanget"
	},
	{
		"english": "chair",
		"batak": "huudulan"
	},
	{
		"english": "cheap",
		"batak": "mura, muranai"
	},
	{
		"english": "children",
		"batak": "ianakkon"
	},
	{
		"english": "cigarettes",
		"batak": "timbaho, sigare"
	},
	{
		"english": "clean",
		"batak": "ias"
	},
	{
		"english": "close",
		"batak": "jenek"
	},
	{
		"english": "comfortable",
		"batak": "lambok"
	},
	{
		"english": "community",
		"batak": "huta"
	},
	{
		"english": "country",
		"batak": "luat"
	},
	{
		"english": "crazy",
		"batak": "rittik, senu"
	},
	{
		"english": "danger",
		"batak": "berbahaya"
	},
	{
		"english": "day",
		"batak": "ari"
	},
	{
		"english": "dead",
		"batak": "mate"
	},
	{
		"english": "deep",
		"batak": "bagas"
	},
	{
		"english": "delicious",
		"batak": "tabo"
	},
	{
		"english": "dirt",
		"batak": "abu"
	},
	{
		"english": "dirty",
		"batak": "homur, hotor"
	},
	{
		"english": "far",
		"batak": "doa"
	},
	{
		"english": "dizzy",
		"batak": "mirdong"
	},
	{
		"english": "doctor",
		"batak": "parubat"
	},
	{
		"english": "dog",
		"batak": "biang"
	},
	{
		"english": "door",
		"batak": "pittu"
	},
	{
		"english": "down",
		"batak": "ditoru"
	},
	{
		"english": "downstairs",
		"batak": "ditoru"
	},
	{
		"english": "dry",
		"batak": "koring"
	},
	{
		"english": "early",
		"batak": "gira"
	},
	{
		"english": "easy",
		"batak": "horup"
	},
	{
		"english": "eight",
		"batak": "walu"
	},
	{
		"english": "eleven",
		"batak": "sappulu sada"
	},
	{
		"english": "empty",
		"batak": "kosong"
	},
	{
		"english": "end",
		"batak": "sukkup"
	},
	{
		"english": "evening",
		"batak": "bokni ari"
	},
	{
		"english": "everything",
		"batak": "sude, sudena"
	},
	{
		"english": "expensive",
		"batak": "arganai, arga"
	},
	{
		"english": "experience",
		"batak": "talenta"
	},
	{
		"english": "family",
		"batak": "pamili"
	},
	{
		"english": "fat",
		"batak": "mok-mok"
	},
	{
		"english": "father",
		"batak": "amang, among"
	},
	{
		"english": "favourite",
		"batak": "lomo, lomoniroha"
	},
	{
		"english": "fear",
		"batak": "mabiar"
	},
	{
		"english": "fever",
		"batak": "mohop"
	},
	{
		"english": "fight (n.)",
		"batak": "marbada"
	},
	{
		"english": "fire",
		"batak": "api"
	},
	{
		"english": "first",
		"batak": "parjolo"
	},
	{
		"english": "five",
		"batak": "lima"
	},
	{
		"english": "floor",
		"batak": "lante"
	},
	{
		"english": "food",
		"batak": "siallangon, sipangan"
	},
	{
		"english": "for",
		"batak": "tu"
	},
	{
		"english": "to",
		"batak": "tu"
	},
	{
		"english": "foreign",
		"batak": "tondong,"
	},
	{
		"english": "forever",
		"batak": "salelengna"
	},
	{
		"english": "four",
		"batak": "opat"
	},
	{
		"english": "free",
		"batak": "pere-pere"
	},
	{
		"english": "fresh",
		"batak": "segar"
	},
	{
		"english": "fried",
		"batak": "nanigoreng"
	},
	{
		"english": "friend",
		"batak": "dongan"
	},
	{
		"english": "from",
		"batak": "sian"
	},
	{
		"english": "fruit",
		"batak": "buah"
	},
	{
		"english": "full",
		"batak": "gok"
	},
	{
		"english": "funny",
		"batak": "pekket"
	},
	{
		"english": "garden",
		"batak": "balian"
	},
	{
		"english": "generous",
		"batak": "mala"
	},
	{
		"english": "girl",
		"batak": "borua"
	},
	{
		"english": "god",
		"batak": "debata"
	},
	{
		"english": "gold",
		"batak": "mas"
	},
	{
		"english": "ingenious",
		"batak": "jago"
	},
	{
		"english": "polite",
		"batak": "burju"
	},
	{
		"english": "government",
		"batak": "pamarenta"
	},
	{
		"english": "greedy",
		"batak": "holit"
	},
	{
		"english": "guitar",
		"batak": "karunjet"
	},
	{
		"english": "handsome",
		"batak": "jogi"
	},
	{
		"english": "happy",
		"batak": "sonang"
	},
	{
		"english": "hard",
		"batak": "karas"
	},
	{
		"english": "difficult",
		"batak": "maol"
	},
	{
		"english": "he",
		"batak": "ibana"
	},
	{
		"english": "head",
		"batak": "ulu, simanjujung"
	},
	{
		"english": "heart",
		"batak": "ate-ate"
	},
	{
		"english": "heavy",
		"batak": "borat"
	},
	{
		"english": "hello",
		"batak": "horas"
	},
	{
		"english": "here",
		"batak": "dison"
	},
	{
		"english": "high",
		"batak": "tibbo"
	},
	{
		"english": "home",
		"batak": "jabu"
	},
	{
		"english": "hot",
		"batak": "mohop"
	},
	{
		"english": "hotel",
		"batak": "panginapan"
	},
	{
		"english": "how",
		"batak": "sadia, piga"
	},
	{
		"english": "human",
		"batak": "jolma, manisia"
	},
	{
		"english": "hungry",
		"batak": "male"
	},
	{
		"english": "hurt",
		"batak": "hassitan"
	},
	{
		"english": "husband",
		"batak": "tunggani doli"
	},
	{
		"english": "i",
		"batak": "ahu"
	},
	{
		"english": "i love you",
		"batak": "Holong do rohangku tu ho"
	},
	{
		"english": "ice",
		"batak": "es"
	},
	{
		"english": "idea",
		"batak": "pandapot"
	},
	{
		"english": "if",
		"batak": "molo"
	},
	{
		"english": "ill/sick",
		"batak": "marsahit"
	},
	{
		"english": "impossible",
		"batak": "ndang hurippu"
	},
	{
		"english": "in",
		"batak": "di"
	},
	{
		"english": "infection",
		"batak": "marnanah"
	},
	{
		"english": "injury",
		"batak": "tarseat"
	},
	{
		"english": "intelligent",
		"batak": "pistar"
	},
	{
		"english": "interesting",
		"batak": "tarnonong"
	},
	{
		"english": "itch",
		"batak": "narasaon"
	},
	{
		"english": "jail",
		"batak": "hurungan"
	},
	{
		"english": "jealous",
		"batak": "late"
	},
	{
		"english": "job",
		"batak": "parkarejoan, parhorjaan"
	},
	{
		"english": "joke",
		"batak": "parekelan"
	},
	{
		"english": "key",
		"batak": "gombok"
	},
	{
		"english": "king",
		"batak": "raja"
	},
	{
		"english": "kiss",
		"batak": "umma"
	},
	{
		"english": "lake",
		"batak": "tao"
	},
	{
		"english": "land",
		"batak": "tano"
	},
	{
		"english": "language",
		"batak": "hata"
	},
	{
		"english": "last",
		"batak": "naparpudi"
	},
	{
		"english": "late",
		"batak": "parpudi"
	},
	{
		"english": "laundry",
		"batak": "manussi"
	},
	{
		"english": "law",
		"batak": "adat"
	},
	{
		"english": "lazy",
		"batak": "malas"
	},
	{
		"english": "left",
		"batak": "hambirang"
	},
	{
		"english": "less",
		"batak": "hurang"
	},
	{
		"english": "letter",
		"batak": "govetan"
	},
	{
		"english": "liar",
		"batak": "pangototoi"
	},
	{
		"english": "life",
		"batak": "mangolu"
	},
	{
		"english": "light",
		"batak": "neang"
	},
	{
		"english": "lighter",
		"batak": "loting"
	},
	{
		"english": "like/similar",
		"batak": "hera"
	},
	{
		"english": "little",
		"batak": "saotik"
	},
	{
		"english": "lock (n.)",
		"batak": "makussi"
	},
	{
		"english": "long",
		"batak": "ganjang"
	},
	{
		"english": "long time",
		"batak": "lelenghian"
	},
	{
		"english": "loud",
		"batak": "gogo"
	},
	{
		"english": "louder",
		"batak": "pagogo-on"
	},
	{
		"english": "lucky",
		"batak": "marnasip lunch"
	},
	{
		"english": "machine",
		"batak": "masin"
	},
	{
		"english": "made",
		"batak": "pinatupa"
	},
	{
		"english": "many",
		"batak": "godang, torop"
	},
	{
		"english": "map",
		"batak": "peta"
	},
	{
		"english": "market",
		"batak": "onan"
	},
	{
		"english": "maybe",
		"batak": "oldora"
	},
	{
		"english": "message",
		"batak": "barita"
	},
	{
		"english": "minute",
		"batak": "satiokin"
	},
	{
		"english": "money",
		"batak": "hepeng"
	},
	{
		"english": "monkey",
		"batak": "bodat"
	},
	{
		"english": "month(s)",
		"batak": "bulan"
	},
	{
		"english": "more",
		"batak": "tambu"
	},
	{
		"english": "morning",
		"batak": "manogot"
	},
	{
		"english": "mother",
		"batak": "inang, inong, omak"
	},
	{
		"english": "mountain",
		"batak": "dolok"
	},
	{
		"english": "name",
		"batak": "goar"
	},
	{
		"english": "never",
		"batak": "nolang hea"
	},
	{
		"english": "new",
		"batak": "imbaru"
	},
	{
		"english": "news",
		"batak": "barita"
	},
	{
		"english": "next",
		"batak": "sahalinai"
	},
	{
		"english": "next week",
		"batak": "minggu nalahoro"
	},
	{
		"english": "night",
		"batak": "borugin"
	},
	{
		"english": "nine",
		"batak": "sia"
	},
	{
		"english": "no",
		"batak": "daong"
	},
	{
		"english": "noise",
		"batak": "gaor"
	},
	{
		"english": "none",
		"batak": "kosong"
	},
	{
		"english": "not yet",
		"batak": "doang dope"
	},
	{
		"english": "nothing",
		"batak": "ndang adong"
	},
	{
		"english": "now",
		"batak": "saonari"
	},
	{
		"english": "ocean",
		"batak": "laut"
	},
	{
		"english": "often",
		"batak": "jot-jot"
	},
	{
		"english": "old",
		"batak": "matua"
	},
	{
		"english": "on",
		"batak": "mangolu"
	},
	{
		"english": "once",
		"batak": "sahali"
	},
	{
		"english": "one",
		"batak": "sada"
	},
	{
		"english": "only",
		"batak": "holan"
	},
	{
		"english": "open",
		"batak": "bukka"
	},
	{
		"english": "opportunity",
		"batak": "kesempatan"
	},
	{
		"english": "opposite",
		"batak": "hata balikna"
	},
	{
		"english": "or",
		"batak": "manang"
	},
	{
		"english": "original",
		"batak": "has/asli"
	},
	{
		"english": "other",
		"batak": "halakna-asing"
	},
	{
		"english": "out",
		"batak": "kawar"
	},
	{
		"english": "painful",
		"batak": "hassitan"
	},
	{
		"english": "paper",
		"batak": "harotas"
	},
	{
		"english": "part",
		"batak": "bagian"
	},
	{
		"english": "party",
		"batak": "pesta"
	},
	{
		"english": "passenger",
		"batak": "sewa/paneimpang"
	},
	{
		"english": "passport",
		"batak": "paspor"
	},
	{
		"english": "past",
		"batak": "naung lalu"
	},
	{
		"english": "peace",
		"batak": "dame"
	},
	{
		"english": "people",
		"batak": "jolma"
	},
	{
		"english": "person",
		"batak": "halak"
	},
	{
		"english": "permission",
		"batak": "parmisi/santabi"
	},
	{
		"english": "pig",
		"batak": "pinahan"
	},
	{
		"english": "place",
		"batak": "inganan"
	},
	{
		"english": "politics",
		"batak": "taktik"
	},
	{
		"english": "poor",
		"batak": "pogos"
	},
	{
		"english": "positive",
		"batak": "positip"
	},
	{
		"english": "power",
		"batak": "hagogo-on"
	},
	{
		"english": "prayer",
		"batak": "martangian"
	},
	{
		"english": "prefer",
		"batak": "lomoniroha"
	},
	{
		"english": "present (time)",
		"batak": "saonari"
	},
	{
		"english": "present/gift",
		"batak": "mangalehon"
	},
	{
		"english": "pretty",
		"batak": "uli"
	},
	{
		"english": "well",
		"batak": "sehat, hipas"
	},
	{
		"english": "price",
		"batak": "arga"
	},
	{
		"english": "priest",
		"batak": "pastor"
	},
	{
		"english": "private",
		"batak": "priyadi"
	},
	{
		"english": "probably",
		"batak": "olodora"
	},
	{
		"english": "problem",
		"batak": "sipikkiran"
	},
	{
		"english": "promise",
		"batak": "marjanji"
	},
	{
		"english": "protect",
		"batak": "manghokkop"
	},
	{
		"english": "province",
		"batak": "propinsi"
	},
	{
		"english": "pull",
		"batak": "manarik"
	},
	{
		"english": "push",
		"batak": "mangunjor"
	},
	{
		"english": "question",
		"batak": "manukkun"
	},
	{
		"english": "quick/quickly",
		"batak": "hatop"
	},
	{
		"english": "quiet",
		"batak": "sip-sip, pasisip"
	},
	{
		"english": "radio",
		"batak": "radio"
	},
	{
		"english": "rain",
		"batak": "udan"
	},
	{
		"english": "raw",
		"batak": "nasohona loppa"
	},
	{
		"english": "nice",
		"batak": "jeges, bulus"
	},
	{
		"english": "ready",
		"batak": "nunga sae"
	},
	{
		"english": "reason",
		"batak": "ulani, alani"
	},
	{
		"english": "receipt",
		"batak": "bon, faktor"
	},
	{
		"english": "recently",
		"batak": "ipe-dope"
	},
	{
		"english": "relationship",
		"batak": "pardonganon"
	},
	{
		"english": "relax",
		"batak": "paulakgogo"
	},
	{
		"english": "religion",
		"batak": "agama"
	},
	{
		"english": "respect",
		"batak": "pasambarhon"
	},
	{
		"english": "responsibility",
		"batak": "tanggungjawab"
	},
	{
		"english": "restaurant",
		"batak": "kode"
	},
	{
		"english": "rice",
		"batak": "idahan (cooked), boras (uncooked)"
	},
	{
		"english": "rich",
		"batak": "mamora"
	},
	{
		"english": "right (not left)",
		"batak": "siamun"
	},
	{
		"english": "right/correct",
		"batak": "situtu, sitohu, sintong"
	},
	{
		"english": "road",
		"batak": "dalan robber/theif"
	},
	{
		"english": "roam",
		"batak": "mardalan, dalani round"
	},
	{
		"english": "roof",
		"batak": "atap"
	},
	{
		"english": "sad",
		"batak": "lungun"
	},
	{
		"english": "safe",
		"batak": "aman"
	},
	{
		"english": "salty",
		"batak": "asin"
	},
	{
		"english": "same",
		"batak": "sarupa"
	},
	{
		"english": "scenery",
		"batak": "panatapan"
	},
	{
		"english": "secret",
		"batak": "sitabunian"
	},
	{
		"english": "selfish",
		"batak": "siginjangroha"
	},
	{
		"english": "serious",
		"batak": "marsitutu"
	},
	{
		"english": "seven",
		"batak": "pitu"
	},
	{
		"english": "several",
		"batak": "piga-piga"
	},
	{
		"english": "shape",
		"batak": "rupana"
	},
	{
		"english": "she",
		"batak": "ibana"
	},
	{
		"english": "short (height)",
		"batak": "metmet"
	},
	{
		"english": "short (time)",
		"batak": "pukkul"
	},
	{
		"english": "shy",
		"batak": "maila"
	},
	{
		"english": "sick",
		"batak": "marsahit"
	},
	{
		"english": "sign",
		"batak": "manekken"
	},
	{
		"english": "similar",
		"batak": "sarupa"
	},
	{
		"english": "single (not married)",
		"batak": "doli-doli (man), anakboru (woman)"
	},
	{
		"english": "situation",
		"batak": "situasi"
	},
	{
		"english": "six",
		"batak": "onom"
	},
	{
		"english": "sleep",
		"batak": "modoni"
	},
	{
		"english": "sleepy/tired",
		"batak": "tartuddu"
	},
	{
		"english": "slow",
		"batak": "nanget/palan"
	},
	{
		"english": "slowly",
		"batak": "nanget-nanget, palan - palan"
	},
	{
		"english": "small",
		"batak": "tagelleng"
	},
	{
		"english": "smell/stench (n.)",
		"batak": "bou, manggus"
	},
	{
		"english": "some",
		"batak": "piga-piga"
	},
	{
		"english": "somebody",
		"batak": "sahalak"
	},
	{
		"english": "something",
		"batak": "adongmai, sesuatu"
	},
	{
		"english": "song",
		"batak": "ende"
	},
	{
		"english": "soon",
		"batak": "sahatopna"
	},
	{
		"english": "sorry",
		"batak": "santabi"
	},
	{
		"english": "souvenir",
		"batak": "tokko ukiran"
	},
	{
		"english": "special",
		"batak": "khusus"
	},
	{
		"english": "spicy",
		"batak": "siak"
	},
	{
		"english": "stack (n.)",
		"batak": "marsitipahan"
	},
	{
		"english": "story",
		"batak": "sarita"
	},
	{
		"english": "straight",
		"batak": "lorus"
	},
	{
		"english": "strange",
		"batak": "aneh, asing"
	},
	{
		"english": "street",
		"batak": "dalan"
	},
	{
		"english": "strong",
		"batak": "gogo, pirma"
	},
	{
		"english": "stupid",
		"batak": "ototo"
	},
	{
		"english": "suddenly",
		"batak": "soppong"
	},
	{
		"english": "sure",
		"batak": "sitoho"
	},
	{
		"english": "surprise",
		"batak": "adong mai"
	},
	{
		"english": "sweet",
		"batak": "manis"
	},
	{
		"english": "tall",
		"batak": "timbo"
	},
	{
		"english": "telephone",
		"batak": "talipon"
	},
	{
		"english": "ten",
		"batak": "sappulu"
	},
	{
		"english": "thanks/thank you",
		"batak": "mauliate"
	},
	{
		"english": "there",
		"batak": "disai"
	},
	{
		"english": "they",
		"batak": "halaki"
	},
	{
		"english": "thick",
		"batak": "tobal"
	},
	{
		"english": "thin",
		"batak": "kurus"
	},
	{
		"english": "thirsty",
		"batak": "mauas"
	},
	{
		"english": "thought",
		"batak": "manurut"
	},
	{
		"english": "three",
		"batak": "tolu"
	},
	{
		"english": "tired",
		"batak": "loja"
	},
	{
		"english": "to (me)",
		"batak": "tu ahu"
	},
	{
		"english": "to (you)",
		"batak": "tuho"
	},
	{
		"english": "to answer",
		"batak": "mangalusi, alusi art"
	},
	{
		"english": "to argue",
		"batak": "martokkar"
	},
	{
		"english": "to be able",
		"batak": "boe/i + verb"
	},
	{
		"english": "to begin",
		"batak": "patwolo"
	},
	{
		"english": "to bite",
		"batak": "mangkarut"
	},
	{
		"english": "to bring",
		"batak": "mamboan, boanon"
	},
	{
		"english": "to bring (a present)",
		"batak": "marsilua"
	},
	{
		"english": "to burn",
		"batak": "manutung"
	},
	{
		"english": "to buy",
		"batak": "manuhor"
	},
	{
		"english": "to carry",
		"batak": "mamboan"
	},
	{
		"english": "to cause (to happen)",
		"batak": "mambahen"
	},
	{
		"english": "to close",
		"batak": "manutup"
	},
	{
		"english": "to come",
		"batak": "ro"
	},
	{
		"english": "to cook",
		"batak": "mangaloppa"
	},
	{
		"english": "to cry",
		"batak": "taritu"
	},
	{
		"english": "to cut",
		"batak": "maneat"
	},
	{
		"english": "to dance",
		"batak": "marjoget"
	},
	{
		"english": "to drink (v.)",
		"batak": "manginum"
	},
	{
		"english": "to eat",
		"batak": "mangallang, mangan"
	},
	{
		"english": "to feel (an emotional state)",
		"batak": "roha"
	},
	{
		"english": "to find",
		"batak": "mandapot, dapot"
	},
	{
		"english": "to forget",
		"batak": "mangalupahon, lupa"
	},
	{
		"english": "to forgive",
		"batak": "manolsoli"
	},
	{
		"english": "to give",
		"batak": "mangalehon"
	},
	{
		"english": "to grow",
		"batak": "manuan"
	},
	{
		"english": "to guess",
		"batak": "mandodo, dodo"
	},
	{
		"english": "to hate",
		"batak": "marsogoniroha, manadikkon"
	},
	{
		"english": "to have",
		"batak": "napuna"
	},
	{
		"english": "to hear",
		"batak": "mambege"
	},
	{
		"english": "to help",
		"batak": "hubantu, mangurupi"
	},
	{
		"english": "to hire/rent",
		"batak": "pasewahon"
	},
	{
		"english": "to hurry",
		"batak": "pahatop"
	},
	{
		"english": "to invite",
		"batak": "manggokhon"
	},
	{
		"english": "to kill",
		"batak": "mamburje"
	},
	{
		"english": "to kiss",
		"batak": "mangummahon"
	},
	{
		"english": "to know",
		"batak": "mamboto, huboto"
	},
	{
		"english": "to laugh",
		"batak": "mengkel"
	},
	{
		"english": "to learn",
		"batak": "marsiajar"
	},
	{
		"english": "to leave",
		"batak": "lao"
	},
	{
		"english": "to like",
		"batak": "lomo"
	},
	{
		"english": "to listen",
		"batak": "mambege"
	},
	{
		"english": "to live",
		"batak": "tinggal"
	},
	{
		"english": "to look",
		"batak": "mamereng"
	},
	{
		"english": "to lose",
		"batak": "hamagoan"
	},
	{
		"english": "to make happen",
		"batak": "mambahen"
	},
	{
		"english": "to marry",
		"batak": "mangalua"
	},
	{
		"english": "to meet",
		"batak": "manjumpangi"
	},
	{
		"english": "to miss",
		"batak": "masihol"
	},
	{
		"english": "to name",
		"batak": "goar"
	},
	{
		"english": "to open",
		"batak": "mambukka"
	},
	{
		"english": "to order/book",
		"batak": "mamesan"
	},
	{
		"english": "to owe",
		"batak": "maminjam owner"
	},
	{
		"english": "to pay",
		"batak": "mambayar"
	},
	{
		"english": "to play",
		"batak": "‘mar’ + verb root"
	},
	{
		"english": "to play (a ball game)",
		"batak": "marbolo"
	},
	{
		"english": "to play a game",
		"batak": "marmeam"
	},
	{
		"english": "to play/make a joke",
		"batak": "margait"
	},
	{
		"english": "to rain",
		"batak": "udan"
	},
	{
		"english": "to read",
		"batak": "manjaha"
	},
	{
		"english": "to receive",
		"batak": "manjalo"
	},
	{
		"english": "to remember",
		"batak": "mangingot, ingot"
	},
	{
		"english": "to rent",
		"batak": "manewa, sewa"
	},
	{
		"english": "to reserve",
		"batak": "paradehon"
	},
	{
		"english": "to rest",
		"batak": "paulak hosa"
	},
	{
		"english": "to return",
		"batak": "paulakhon, mulak"
	},
	{
		"english": "to save",
		"batak": "manimpan"
	},
	{
		"english": "to say",
		"batak": "mandok"
	},
	{
		"english": "to search",
		"batak": "mangalului"
	},
	{
		"english": "to see",
		"batak": "mamereng, mangida"
	},
	{
		"english": "to sell",
		"batak": "manjual"
	},
	{
		"english": "to send",
		"batak": "mangirim"
	},
	{
		"english": "to share",
		"batak": "mambagi"
	},
	{
		"english": "to shout",
		"batak": "manjou"
	},
	{
		"english": "to show",
		"batak": "patuduhon"
	},
	{
		"english": "to shut",
		"batak": "mambodil"
	},
	{
		"english": "to sing",
		"batak": "marlogu"
	},
	{
		"english": "to sit",
		"batak": "hundul"
	},
	{
		"english": "to sleep",
		"batak": "laho modom"
	},
	{
		"english": "to smile",
		"batak": "mekkel"
	},
	{
		"english": "to speak",
		"batak": "makkatai"
	},
	{
		"english": "to start",
		"batak": "mamulai"
	},
	{
		"english": "to stay",
		"batak": "tinggal"
	},
	{
		"english": "to steal",
		"batak": "manakko"
	},
	{
		"english": "to stop",
		"batak": "pasitoppon"
	},
	{
		"english": "to swim",
		"batak": "marlange"
	},
	{
		"english": "to take/carry",
		"batak": "mamboan"
	},
	{
		"english": "to talk",
		"batak": "makkatai"
	},
	{
		"english": "to taste",
		"batak": "mandai"
	},
	{
		"english": "to teach",
		"batak": "mangajari"
	},
	{
		"english": "to think",
		"batak": "mamikkiri, pikkiri"
	},
	{
		"english": "to touch",
		"batak": "manondong, maniop, manjamah"
	},
	{
		"english": "to translate",
		"batak": "manorangkoh"
	},
	{
		"english": "to trek",
		"batak": "mandaki"
	},
	{
		"english": "to try (a dish)",
		"batak": "mandai"
	},
	{
		"english": "to try/test",
		"batak": "manorong, manubah"
	},
	{
		"english": "to visit",
		"batak": "martondong"
	},
	{
		"english": "to wait",
		"batak": "mamette"
	},
	{
		"english": "to walk",
		"batak": "mardalan"
	},
	{
		"english": "to want",
		"batak": "laho"
	},
	{
		"english": "to wash",
		"batak": "manussi"
	},
	{
		"english": "to watch",
		"batak": "mamereng"
	},
	{
		"english": "to win",
		"batak": "monang"
	},
	{
		"english": "to work",
		"batak": "karejo"
	},
	{
		"english": "to write",
		"batak": "manurat"
	},
	{
		"english": "toilet",
		"batak": "vehseh, WC"
	},
	{
		"english": "tondong town",
		"batak": "kota"
	},
	{
		"english": "tonight",
		"batak": "bodari"
	},
	{
		"english": "too/also",
		"batak": "dohot"
	},
	{
		"english": "tooth",
		"batak": "ngingi"
	},
	{
		"english": "torch/flashlight",
		"batak": "senter"
	},
	{
		"english": "tour",
		"batak": "mardallan-dalani"
	},
	{
		"english": "tourist",
		"batak": "tama"
	},
	{
		"english": "trip",
		"batak": "tirip"
	},
	{
		"english": "true",
		"batak": "situho, situtu"
	},
	{
		"english": "trust",
		"batak": "porsea"
	},
	{
		"english": "twelve",
		"batak": "sappulu dua"
	},
	{
		"english": "two",
		"batak": "dua"
	},
	{
		"english": "vacation",
		"batak": "lowongan"
	},
	{
		"english": "valley",
		"batak": "ramba-ramba"
	},
	{
		"english": "valuable",
		"batak": "arta naummarga"
	},
	{
		"english": "value",
		"batak": "arta"
	},
	{
		"english": "very",
		"batak": "suffix ‘"
	},
	{
		"english": "view",
		"batak": "panatapan"
	},
	{
		"english": "village",
		"batak": "huta"
	},
	{
		"english": "vomit",
		"batak": "muta"
	},
	{
		"english": "warm",
		"batak": "las"
	},
	{
		"english": "water",
		"batak": "aek, mual"
	},
	{
		"english": "waterfall",
		"batak": "binanga"
	},
	{
		"english": "we (exclusive)",
		"batak": "hami"
	},
	{
		"english": "we (inclusive)",
		"batak": "hita"
	},
	{
		"english": "weather",
		"batak": "suassa"
	},
	{
		"english": "wet",
		"batak": "maraek"
	},
	{
		"english": "what",
		"batak": "aha"
	},
	{
		"english": "what time",
		"batak": "pukkul piga"
	},
	{
		"english": "when",
		"batak": "andigan (present time), nandigan (past time)"
	},
	{
		"english": "where",
		"batak": "di-dia, hu-dia, tu-dia"
	},
	{
		"english": "who",
		"batak": "ise"
	},
	{
		"english": "whole",
		"batak": "lobang"
	},
	{
		"english": "why",
		"batak": "alani aha"
	},
	{
		"english": "wide",
		"batak": "luas"
	},
	{
		"english": "wife",
		"batak": "pardijabu, inang-inang"
	},
	{
		"english": "wind",
		"batak": "alogo"
	},
	{
		"english": "wire",
		"batak": "kawat"
	},
	{
		"english": "wise",
		"batak": "pistar"
	},
	{
		"english": "with",
		"batak": "dohot"
	},
	{
		"english": "without",
		"batak": "ndang pola"
	},
	{
		"english": "wood",
		"batak": "hau"
	},
	{
		"english": "woods/jungle",
		"batak": "hau"
	},
	{
		"english": "world",
		"batak": "portibi"
	},
	{
		"english": "wrong",
		"batak": "ndang sintong"
	},
	{
		"english": "year",
		"batak": "taon"
	},
	{
		"english": "yes",
		"batak": "olo"
	},
	{
		"english": "yesterday",
		"batak": "nattoari"
	},
	{
		"english": "yet",
		"batak": "ndaong dope"
	},
	{
		"english": "you (pl.)",
		"batak": "hamu sudena, hamuna"
	},
	{
		"english": "you (sg.)",
		"batak": "ho, ko"
	},
	{
		"english": "young",
		"batak": "poso"
	},
	{
		"english": "young man/girl (a youth )",
		"batak": "naposo bulung"
	}
]